.editorconfig
.gitignore
.gitlab-ci.yml
LICENSE
README.rst
publish.settings.sh
publish.sh
pyproject.toml
.idea/modules.xml
.idea/peek-agent-service.iml
.idea/inspectionProfiles/Project_Default.xml
.idea/inspectionProfiles/profiles_settings.xml
peek_agent_service/PeekAgentConfig.py
peek_agent_service/PeekAgentConfigTest.py
peek_agent_service/PlatformDependencyTest.py
peek_agent_service/__init__.py
peek_agent_service/run_peek_agent_service.py
peek_agent_service/winsvc_peek_agent_service.py
peek_agent_service.egg-info/PKG-INFO
peek_agent_service.egg-info/SOURCES.txt
peek_agent_service.egg-info/dependency_links.txt
peek_agent_service.egg-info/entry_points.txt
peek_agent_service.egg-info/requires.txt
peek_agent_service.egg-info/top_level.txt
peek_agent_service/plugin/AgentPluginLoader.py
peek_agent_service/plugin/AgentPluginLoaderTest.py
peek_agent_service/plugin/PeekAgentPlatformHook.py
peek_agent_service/plugin/__init__.py
peek_agent_service/sw_install/PeekSwInstallManager.py
peek_agent_service/sw_install/PluginSwInstallManager.py
peek_agent_service/sw_install/__init__.py