Metadata-Version: 2.4
Name: peek-agent-service
Version: 5.0.4
Summary: Peek Agent Service - where Peek Apps can run their I/O code
Author-email: Synerty <contact@synerty.com>
Project-URL: Homepage, https://github.com/Synerty/peek-agent-service
Keywords: Peek,Python,Platform,synerty
License-File: LICENSE
Requires-Dist: peek-plugin-base==5.0.4
Requires-Dist: peek-platform==5.0.4
Dynamic: license-file
